grpredict/__init__.py
grpredict-25.6.1.dist-info/licenses/LICENSE
grpredict-25.6.1.dist-info/METADATA
grpredict-25.6.1.dist-info/WHEEL
grpredict-25.6.1.dist-info/top_level.txt
grpredict-25.6.1.dist-info/RECORD
